acdc_py/GS.py
acdc_py/SA.py
acdc_py/_SA_GS_subfunctions.py
acdc_py/__init__.py
acdc_py/_condense_diffuse_funcs.py
acdc_py/_diffuse_correction_funcs.py
acdc_py/_dual_annealing_with_progress_bar.py
acdc_py/_get_opt.py
acdc_py/_iter_clust.py
acdc_py/_pl.py
acdc_py/_pp.py
acdc_py/_tl.py
acdc_py/config.py
acdc_py/get_opt.py
acdc_py/pl.py
acdc_py/pp.py
acdc_py/tl.py
acdc_py-1.1.4.dist-info/LICENSE
acdc_py-1.1.4.dist-info/METADATA
acdc_py-1.1.4.dist-info/WHEEL
acdc_py-1.1.4.dist-info/top_level.txt
acdc_py-1.1.4.dist-info/RECORD
