Metadata-Version: 2.1
Name: acdc-py
Version: 1.1.4
Summary: A package to quickly identify unbiased graph-based clusterings via parameter optimization in Python
Home-page: https://github.com/califano-lab/acdc_py
Author: Alexander L.E. Wang & Luca Zanella & Alessandro Vasciaveo
Author-email: aw3436@cumc.columbia.edu
License: MIT
Project-URL: Documentation, https://acdc.readthedocs.io/en/latest/
Project-URL: Source, https://github.com/califano-lab/acdc_py
Platform: UNKNOWN
Requires-Python: >=3.8
Requires-Dist: scipy
Requires-Dist: tqdm
Requires-Dist: scanpy
Requires-Dist: anndata
Requires-Dist: pandas
Requires-Dist: numpy
Requires-Dist: joblib
Requires-Dist: leidenalg
Requires-Dist: scikit-learn
Requires-Dist: matplotlib
Requires-Dist: seaborn
Requires-Dist: datetime
Requires-Dist: nbsphinx
